airflow/providers/oras/__init__.py
airflow/providers/oras/get_provider_info.py
airflow/providers/oras/bundles/__init__.py
airflow/providers/oras/bundles/oras.py
airflow/providers/oras/hooks/__init__.py
airflow/providers/oras/hooks/oras.py
apache_airflow_providers_oras-0.0.4.dist-info/entry_points.txt
apache_airflow_providers_oras-0.0.4.dist-info/licenses/LICENSE
apache_airflow_providers_oras-0.0.4.dist-info/licenses/NOTICE
apache_airflow_providers_oras-0.0.4.dist-info/WHEEL
apache_airflow_providers_oras-0.0.4.dist-info/METADATA
apache_airflow_providers_oras-0.0.4.dist-info/RECORD
