Metadata-Version: 2.4
Name: apache-airflow-providers-oras
Version: 0.0.4
Summary: Provider package apache-airflow-providers-oras for Apache Airflow
Keywords: airflow-provider,oras,airflow,integration
Author-email: Apache Software Foundation <dev@airflow.apache.org>
Maintainer-email: Apache Software Foundation <dev@airflow.apache.org>
Requires-Python: >=3.10
License-Expression: Apache-2.0
Classifier: Development Status :: 5 - Production/Stable
Classifier: Environment :: Console
Classifier: Environment :: Web Environment
Classifier: Intended Audience :: Developers
Classifier: Intended Audience :: System Administrators
Classifier: Framework :: Apache Airflow
Classifier: Framework :: Apache Airflow :: Provider
Classifier: Programming Language :: Python :: 3.10
Classifier: Programming Language :: Python :: 3.11
Classifier: Programming Language :: Python :: 3.12
Classifier: Programming Language :: Python :: 3.13
Classifier: Topic :: System :: Monitoring
License-File: LICENSE
License-File: NOTICE
Requires-Dist: apache-airflow>=3.0.0
Requires-Dist: oras>=0.2.38
Requires-Dist: docker ; extra == "all"
Requires-Dist: boto3 ; extra == "all"
Requires-Dist: docker ; extra == "docker"
Requires-Dist: boto3 ; extra == "ecr"
Project-URL: Bug Tracker, https://github.com/apache/airflow/issues
Project-URL: Changelog, https://airflow.apache.org/docs/apache-airflow-providers-oras/0.0.4/changelog.html
Project-URL: Documentation, https://airflow.apache.org/docs/apache-airflow-providers-oras/0.0.4
Project-URL: Mastodon, https://fosstodon.org/@airflow
Project-URL: Slack Chat, https://s.apache.org/airflow-slack
Project-URL: Source Code, https://github.com/apache/airflow
Project-URL: YouTube, https://www.youtube.com/channel/UCSXwxpWZQ7XZ1WL3wqevChA/
Provides-Extra: all
Provides-Extra: docker
Provides-Extra: ecr
